{"entries":[{"playerName":"haichuott","playerDisplayName":"haichuott§r","prefix":"","suffix":"","playerID":"30fced2e-8d7c-3648-8130-1d53ee715c3a","position":1,"board":"statistic_damage_dealt","type":"DAILY","score":2546.0},{"playerName":"truong","playerDisplayName":"truong§r","prefix":"","suffix":"","playerID":"183148db-2b6c-3fce-b85e-e70a1831813e","position":2,"board":"statistic_damage_dealt","type":"DAILY","score":0.0},{"playerName":"charactermanhwa","playerDisplayName":"§4charactermanhwa§r","prefix":"","suffix":"","playerID":"51d2bc03-0078-3fec-98a9-4b160b2996fc","position":3,"board":"statistic_damage_dealt","type":"DAILY","score":0.0},{"playerName":"botruong","playerDisplayName":"§4botruong§r","prefix":"","suffix":"","playerID":"6b3e5ee8-05c3-30a3-b7d7-1434fdeccbef","position":4,"board":"statistic_damage_dealt","type":"DAILY","score":0.0},{"playerName":"HunZep","playerDisplayName":"§x§b§c§f§f§d§8A§x§b§6§f§3§d§fD§x§b§0§e§6§e§6M§x§a§a§d§a§e§dI§x§a§4§c§e§f§4N§x§9§e§c§1§f§bx§x§a§4§a§a§e§dH§x§b§6§8§8§c§9u§x§c§8§6§6§a§5n§x§d§b§4§4§8§0Z§x§e§d§2§2§5§ce§x§f§f§0§0§3§8p§r","prefix":"","suffix":"","playerID":"a138b827-dc5b-3184-9f78-9a582c6d45d0","position":5,"board":"statistic_damage_dealt","type":"DAILY","score":0.0},{"playerName":"---","playerDisplayName":"---","prefix":"","suffix":"","position":6,"board":"statistic_damage_dealt","type":"DAILY","score":-1.0},{"playerName":"---","playerDisplayName":"---","prefix":"","suffix":"","position":7,"board":"statistic_damage_dealt","type":"DAILY","score":-1.0},{"playerName":"---","playerDisplayName":"---","prefix":"","suffix":"","position":8,"board":"statistic_damage_dealt","type":"DAILY","score":-1.0},{"playerName":"---","playerDisplayName":"---","prefix":"","suffix":"","position":9,"board":"statistic_damage_dealt","type":"DAILY","score":-1.0},{"playerName":"---","playerDisplayName":"---","prefix":"","suffix":"","position":10,"board":"statistic_damage_dealt","type":"DAILY","score":-1.0}],"meta":{"time":1709946985120,"type":"DAILY","board":"statistic_damage_dealt"}}